[
  {
    "id": "ex-orland-park-il",
    "address": "14132 Trenton Ave, Orland Park, IL 60462",
    "lat": 41.63322670000001,
    "lng": -87.8431279,
    "kind": "example",
    "msbuildings": {
      "centroidDist_m": 1.25,
      "footprint_m2": 269.64,
      "footprint_sqft": 2902.4,
      "polygon_lonlat": [
        [
          -87.843263,
          41.633255
        ],
        [
          -87.84326,
          41.633162
        ],
        [
          -87.843031,
          41.633166
        ],
        [
          -87.843033,
          41.633217
        ],
        [
          -87.843008,
          41.633217
        ],
        [
          -87.843011,
          41.633306
        ],
        [
          -87.843157,
          41.633304
        ],
        [
          -87.843155,
          41.633257
        ],
        [
          -87.843263,
          41.633255
        ]
      ],
      "n_candidates": 99
    }
  },
  {
    "id": "nb-orland-park-il-0",
    "address": "14108 Concord Dr, Orland Park, IL 60462, USA",
    "lat": 41.63393566490666,
    "lng": -87.84296826446003,
    "kind": "neighbor",
    "msbuildings": {
      "centroidDist_m": 14.42,
      "footprint_m2": 290.18,
      "footprint_sqft": 3123.5,
      "polygon_lonlat": [
        [
          -87.843267,
          41.633915
        ],
        [
          -87.843272,
          41.633818
        ],
        [
          -87.843036,
          41.633811
        ],
        [
          -87.843034,
          41.633859
        ],
        [
          -87.843004,
          41.633858
        ],
        [
          -87.842999,
          41.633955
        ],
        [
          -87.843145,
          41.63396
        ],
        [
          -87.843148,
          41.633911
        ],
        [
          -87.843267,
          41.633915
        ]
      ],
      "n_candidates": 90
    }
  },
  {
    "id": "nb-orland-park-il-1",
    "address": "14148 Yorktown Dr, Orland Park, IL 60462, USA",
    "lat": 41.63271213060295,
    "lng": -87.84407404852548,
    "kind": "neighbor",
    "msbuildings": {
      "centroidDist_m": 18.78,
      "footprint_m2": 266.37,
      "footprint_sqft": 2867.1,
      "polygon_lonlat": [
        [
          -87.844386,
          41.632753
        ],
        [
          -87.844148,
          41.632759
        ],
        [
          -87.84415,
          41.632807
        ],
        [
          -87.844126,
          41.632807
        ],
        [
          -87.844129,
          41.632892
        ],
        [
          -87.844274,
          41.632888
        ],
        [
          -87.844272,
          41.632848
        ],
        [
          -87.84439,
          41.632845
        ],
        [
          -87.844386,
          41.632753
        ]
      ],
      "n_candidates": 95
    }
  }
]